MANIFEST.in
setup.py
musicnow/__init__.py
musicnow/albumsearch.py
musicnow/command_line.py
musicnow/config.ini
musicnow/improvename.py
musicnow/log.py
musicnow/repair.py
musicnow.egg-info/PKG-INFO
musicnow.egg-info/SOURCES.txt
musicnow.egg-info/dependency_links.txt
musicnow.egg-info/entry_points.txt
musicnow.egg-info/requires.txt
musicnow.egg-info/top_level.txt