Metadata-Version: 1.0
Name: musicnow
Version: 5.2.0
Summary: Lets you download music with album art and metadata
Home-page: https://github.com/lakshaykalbhor/MusicNow
Author: Lakshay Kalbhor
Author-email: lakshaykalbhor@gmail.com
License: MIT
Platform: UNKNOWN
